pylibaryscrape/__init__.py
pylibaryscrape-1.0.0.dist-info/METADATA
pylibaryscrape-1.0.0.dist-info/WHEEL
pylibaryscrape-1.0.0.dist-info/top_level.txt
pylibaryscrape-1.0.0.dist-info/RECORD
