Metadata-Version: 2.1
Name: pylibaryscrape
Version: 1.0.0
Summary: Package that helps with scraping other packages
Home-page: UNKNOWN
Author: NHJonas
Author-email: NHJonas@gmail.com
License: UNKNOWN
Keywords: python
Platform: UNKNOWN
Classifier: Operating System :: Microsoft :: Windows
